setup.py
zlist/__init__.py
zlist/_version.py
zlist/main.py
zlist.egg-info/PKG-INFO
zlist.egg-info/SOURCES.txt
zlist.egg-info/dependency_links.txt
zlist.egg-info/entry_points.txt
zlist.egg-info/requires.txt
zlist.egg-info/top_level.txt