Metadata-Version: 1.0
Name: zlist
Version: 2.0.1
Summary: Parses your CSS files for z-index declarations and builds an ordered list of them.
Home-page: http://github.com/BigglesZX/zlist
Author: James Tiplady
Author-email: UNKNOWN
License: UNKNOWN
Platform: UNKNOWN
Classifier: Development Status :: 4 - Beta
Classifier: Environment :: Console
Classifier: Intended Audience :: Information Technology
Classifier: Operating System :: MacOS :: MacOS X
Classifier: Operating System :: Unix
Classifier: Operating System :: POSIX
Classifier: Operating System :: Microsoft :: Windows
Classifier: Programming Language :: Python
Classifier: Programming Language :: Python :: 2.6
Classifier: Programming Language :: Python :: 2.7
Classifier: Topic :: Software Development :: Quality Assurance
Classifier: Topic :: Utilities
